elrahapi/__init__.py
elrahapi/__main__.py
elrahapi/authentication/__init__.py
elrahapi/authentication/authentication_manager.py
elrahapi/authentication/authentication_namespace.py
elrahapi/authentication/authentication_router_provider.py
elrahapi/authentication/token.py
elrahapi/authorization/__init__.py
elrahapi/authorization/base_meta_model.py
elrahapi/authorization/privilege/__init__.py
elrahapi/authorization/privilege/meta_models.py
elrahapi/authorization/privilege/models.py
elrahapi/authorization/privilege/schemas.py
elrahapi/authorization/role/__init__.py
elrahapi/authorization/role/meta_models.py
elrahapi/authorization/role/models.py
elrahapi/authorization/role/schemas.py
elrahapi/authorization/role_privilege/__init__.py
elrahapi/authorization/role_privilege/meta_models.py
elrahapi/authorization/role_privilege/models.py
elrahapi/authorization/role_privilege/schemas.py
elrahapi/authorization/user_privilege/__init__.py
elrahapi/authorization/user_privilege/meta_models.py
elrahapi/authorization/user_privilege/models.py
elrahapi/authorization/user_privilege/schemas.py
elrahapi/authorization/user_role/__init__.py
elrahapi/authorization/user_role/meta_models.py
elrahapi/authorization/user_role/models.py
elrahapi/authorization/user_role/schemas.py
elrahapi/crud/__init__.py
elrahapi/crud/bulk_models.py
elrahapi/crud/crud_forgery.py
elrahapi/crud/crud_models.py
elrahapi/database/__init__.py
elrahapi/database/database_constants.py
elrahapi/database/database_manager.py
elrahapi/database/seed_manager.py
elrahapi/database/session_manager.py
elrahapi/elrahsettings/__init__.py
elrahapi/elrahsettings/models.py
elrahapi/exception/__init__.py
elrahapi/exception/auth_exception.py
elrahapi/exception/custom_http_exception.py
elrahapi/exception/exceptions_utils.py
elrahapi/main/.env
elrahapi/main/.env.example
elrahapi/main/__init__.py
elrahapi/main/main.py
elrahapi/main/seed.py
elrahapi/main/main_project_files/.gitignore
elrahapi/main/main_project_files/README.md
elrahapi-1.2.1.6.dist-info/METADATA
elrahapi-1.2.1.6.dist-info/WHEEL
elrahapi-1.2.1.6.dist-info/entry_points.txt
elrahapi-1.2.1.6.dist-info/top_level.txt
elrahapi-1.2.1.6.dist-info/RECORD
