Metadata-Version: 2.4
Name: elrahapi
Version: 1.2.1.6
Summary: Package de développement d'API basé FastAPI
Home-page: https://github.com/Harlequelrah/Library-ElrahAPI
Author: Harlequelrah
Author-email: maximeatsoudegbovi@gmail.com
License: LGPL-3.0-only
Requires-Python: >=3.10
Requires-Dist: fastapi[standard]>=0.128.0
Requires-Dist: alembic>=1.13.3
Requires-Dist: argon2-cffi>=23.1.0
Requires-Dist: python-jose[cryptography]>=3.3.0
Requires-Dist: black>=24.10.0
Requires-Dist: sqlalchemy>=2.0.38
Requires-Dist: sqlalchemy-utils>=0.41.2
Requires-Dist: aiosqlite>=0.21.0
Dynamic: author
Dynamic: author-email
Dynamic: description
Dynamic: description-content-type
Dynamic: home-page
Dynamic: license
Dynamic: requires-dist
Dynamic: requires-python
Dynamic: summary
